serial_communicator.py
serial_communicator-1.0.0.dist-info/LICENSE
serial_communicator-1.0.0.dist-info/METADATA
serial_communicator-1.0.0.dist-info/WHEEL
serial_communicator-1.0.0.dist-info/top_level.txt
serial_communicator-1.0.0.dist-info/RECORD
