Metadata-Version: 2.1
Name: serial-communicator
Version: 1.0.0
Summary: Модуль для взаимодействия с устройствами через последовательный порт.
Home-page: https://github.com/RadioPizza/serial_communicator
Author: Oleg Kravtsov
Author-email: kravtsov.oleg@vk.com
License: MIT
Classifier: Programming Language :: Python :: 3
Classifier: License :: OSI Approved :: MIT License
Classifier: Operating System :: OS Independent
Requires-Python: >=3.6
License-File: LICENSE
Requires-Dist: pyserial
